transferwee/__init__.py
transferwee/transferwee.py
transferwee-1.0.2.dist-info/METADATA
transferwee-1.0.2.dist-info/WHEEL
transferwee-1.0.2.dist-info/entry_points.txt
transferwee-1.0.2.dist-info/top_level.txt
transferwee-1.0.2.dist-info/RECORD
