Metadata-Version: 2.1
Name: transferwee
Version: 1.0.2
Summary: Download/upload files via wetransfer.com
Home-page: https://github.com/iamleot/transferwee
Author: Leonardo Taccari
Author-email: iamleot@email.com
License: MIT
Classifier: Programming Language :: Python :: 3
Classifier: License :: OSI Approved :: MIT License
Classifier: Operating System :: OS Independent
Requires-Dist: requests
